cli/__init__.py
cli/sg.py
scalegrid_cli-1.1.0.dist-info/LICENSE
scalegrid_cli-1.1.0.dist-info/METADATA
scalegrid_cli-1.1.0.dist-info/WHEEL
scalegrid_cli-1.1.0.dist-info/entry_points.txt
scalegrid_cli-1.1.0.dist-info/top_level.txt
scalegrid_cli-1.1.0.dist-info/RECORD
