Metadata-Version: 2.1
Name: scalegrid-cli
Version: 1.1.0
Summary: ScaleGrid CLI
Home-page: UNKNOWN
License: GPL
Keywords: scalegrid database mongo redis mysql postgresql
Platform: UNKNOWN
Classifier: Development Status :: 5 - Production/Stable
Classifier: Intended Audience :: Developers
Classifier: Topic :: Internet
Classifier: License :: OSI Approved :: GNU Affero General Public License v3
Classifier: Programming Language :: Python :: 3
Requires-Python: >=3
Requires-Dist: docopt (==0.6.2)
